fungivision/__init__.py
fungivision/wrapper.py
fungivision/config/__init__.py
fungivision/config/dino.py
fungivision/config/kl.py
fungivision/config/simclr.py
fungivision/gradients/__init__.py
fungivision/gradients/base_extractor.py
fungivision/gradients/kl_extractor.py
fungivision/gradients/dino/__init__.py
fungivision/gradients/dino/extractor.py
fungivision/gradients/dino/transforms.py
fungivision/gradients/simclr/__init__.py
fungivision/gradients/simclr/extractor.py
fungivision/gradients/simclr/transforms.py
fungivision/utils/__init__.py
fungivision/utils/autograd_hacks.py
fungivision/utils/compression.py
fungivision/utils/misc.py
fungivision-0.0.2.dist-info/LICENSE.txt
fungivision-0.0.2.dist-info/WHEEL
fungivision-0.0.2.dist-info/METADATA
fungivision-0.0.2.dist-info/RECORD
