Metadata-Version: 2.1
Name: fungivision
Version: 0.0.2
Summary: FUNGI: Features from UNsupervised GradIents
Author-email: Walter Simoncini <walter@ashita.nl>
Requires-Python: >=3.10
Classifier: Programming Language :: Python :: 3
Classifier: License :: OSI Approved :: MIT License
Classifier: Operating System :: OS Independent
Requires-Dist: torch>=2.3.1
Requires-Dist: torchvision>=0.18.1
Requires-Dist: tqdm>=4.66.4
